aidlc_mcp_tools/__init__.py
aidlc_mcp_tools/cli.py
aidlc_mcp_tools/config.py
aidlc_mcp_tools/server.py
aidlc_mcp_tools/tools.py
aidlc_mcp_tools-1.2.1.dist-info/METADATA
aidlc_mcp_tools-1.2.1.dist-info/WHEEL
aidlc_mcp_tools-1.2.1.dist-info/entry_points.txt
aidlc_mcp_tools-1.2.1.dist-info/RECORD
