Metadata-Version: 2.4
Name: aidlc-mcp-tools
Version: 1.2.1
Summary: AIDLC Dashboard MCP Tools for Amazon Q integration
Author-email: AIDLC Team <team@aidlc.dev>
Requires-Python: >=3.11
Requires-Dist: flask-cors>=4.0.0
Requires-Dist: flask>=2.3.3
Requires-Dist: requests>=2.31.0
Provides-Extra: dev
Requires-Dist: black>=23.0.0; extra == 'dev'
Requires-Dist: isort>=5.12.0; extra == 'dev'
Requires-Dist: pytest>=7.0.0; extra == 'dev'
